{
	"page": 1,
	"total_results": 10000,
	"total_pages": 500,
	"results": [
		{
			"popularity": 65.376,
			"known_for_department": "Acting",
			"name": "Keanu Reeves",
			"id": 6384,
			"profile_path": "/d9HyjGMCt4wgJIOxAGlaYWhKsiN.jpg",
			"adult": false,
			"known_for": [
				{
					"poster_path": "/dXNAPwY7VrqMAo51EKhhCJfaGb5.jpg",
					"vote_count": 17790,
					"video": false,
					"media_type": "movie",
					"id": 603,
					"adult": false,
					"backdrop_path": "/fNG7i7RqMErkcqhohV2a6cV1Ehy.jpg",
					"original_language": "en",
					"original_title": "The Matrix",
					"genre_ids": [28, 878],
					"title": "The Matrix",
					"vote_average": 8.1,
					"overview": "Set in the 22nd century, The Matrix tells the story of a computer hacker who joins a group of underground insurgents fighting the vast and powerful computers who now rule the earth.",
					"release_date": "1999-03-30"
				},
				{
					"poster_path": "/h3VxEVUOoBZmo79O8RqKvyGiqmE.jpg",
					"vote_count": 13254,
					"video": false,
					"media_type": "movie",
					"id": 245891,
					"adult": false,
					"backdrop_path": "/7dzngS8pLkGJpyeskCFcjPO9qLF.jpg",
					"original_language": "en",
					"original_title": "John Wick",
					"genre_ids": [28, 53],
					"title": "John Wick",
					"vote_average": 7.3,
					"overview": "Ex-hitman John Wick comes out of retirement to track down the gangsters that took everything from him.",
					"release_date": "2014-10-22"
				},
				{
					"poster_path": "/hXWBc0ioZP3cN4zCu6SN3YHXZVO.jpg",
					"vote_count": 8280,
					"video": false,
					"media_type": "movie",
					"id": 324552,
					"adult": false,
					"backdrop_path": "/fRLftkwv8jm3DLxXOf2NbngHjPB.jpg",
					"original_language": "en",
					"original_title": "John Wick: Chapter 2",
					"genre_ids": [28, 80, 53],
					"title": "John Wick: Chapter 2",
					"vote_average": 7.2,
					"overview": "John Wick is forced out of retirement by a former associate looking to seize control of a shadowy international assassins’ guild. Bound by a blood oath to aid him, Wick travels to Rome and does battle against some of the world’s most dangerous killers.",
					"release_date": "2017-02-08"
				}
			],
			"gender": 2
		},
		{
			"popularity": 59.951,
			"known_for_department": "Acting",
			"name": "Jason Statham",
			"id": 976,
			"profile_path": "/lldeQ91GwIVff43JBrpdbAAeYWj.jpg",
			"adult": false,
			"known_for": [
				{
					"vote_count": 8127,
					"id": 82992,
					"video": false,
					"media_type": "movie",
					"vote_average": 6.8,
					"title": "Fast & Furious 6",
					"release_date": "2013-05-21",
					"original_language": "en",
					"original_title": "Fast & Furious 6",
					"genre_ids": [28, 53, 80],
					"backdrop_path": "/mRfI3y2oAd7ejur2di09xC9niqp.jpg",
					"adult": false,
					"overview": "Hobbs has Dominic and Brian reassemble their crew to take down a team of mercenaries: Dominic unexpectedly gets convoluted also facing his presumed deceased girlfriend, Letty.",
					"poster_path": "/n31VRDodbaZxkrZmmzyYSFNVpW5.jpg"
				},
				{
					"poster_path": "/jPFsjmFlTFmpIY41BP3C4sVYOKw.jpg",
					"vote_count": 7805,
					"video": false,
					"media_type": "movie",
					"id": 168259,
					"adult": false,
					"backdrop_path": "/ajCVA8NZY2mjaONBrvNFEvrTwPH.jpg",
					"original_language": "en",
					"original_title": "Furious 7",
					"genre_ids": [28, 53],
					"title": "Furious 7",
					"vote_average": 7.3,
					"overview": "Deckard Shaw seeks revenge against Dominic Toretto and his family for his comatose brother.",
					"release_date": "2015-04-01"
				},
				{
					"poster_path": "/dImWM7GJqryWJO9LHa3XQ8DD5NH.jpg",
					"vote_count": 7628,
					"video": false,
					"media_type": "movie",
					"id": 337339,
					"adult": false,
					"backdrop_path": "/jzdnhRhG0dsuYorwvSqPqqnM1cV.jpg",
					"original_language": "en",
					"original_title": "The Fate of the Furious",
					"genre_ids": [28, 80, 53],
					"title": "The Fate of the Furious",
					"vote_average": 6.9,
					"overview": "When a mysterious woman seduces Dom into the world of crime and a betrayal of those closest to him, the crew face trials that will test them as never before.",
					"release_date": "2017-04-12"
				}
			],
			"gender": 2
		},
		{
			"popularity": 58.185,
			"known_for_department": "Acting",
			"name": "Erin Moriarty",
			"id": 990393,
			"profile_path": "/eJpdao8KKdcs08U8YMA68HD5kxg.jpg",
			"adult": false,
			"known_for": [
				{
					"poster_path": "/2sFME73GaD8UsUxPUKe60cPdLif.jpg",
					"vote_count": 4532,
					"video": false,
					"media_type": "movie",
					"id": 334533,
					"adult": false,
					"backdrop_path": "/tMyVb5CXHnBLQ8V7s0FuFA5V9nP.jpg",
					"original_language": "en",
					"original_title": "Captain Fantastic",
					"genre_ids": [12, 18],
					"title": "Captain Fantastic",
					"vote_average": 8,
					"overview": "A father living in the forests of the Pacific Northwest with his six young kids tries to assimilate back into society.",
					"release_date": "2016-07-02"
				},
				{
					"original_name": "The Boys",
					"genre_ids": [10759, 10765],
					"media_type": "tv",
					"name": "The Boys",
					"origin_country": ["US"],
					"vote_count": 2329,
					"first_air_date": "2019-07-25",
					"backdrop_path": "/mGVrXeIjyecj6TKmwPVpHlscEmw.jpg",
					"original_language": "en",
					"id": 76479,
					"vote_average": 8.4,
					"overview": "A group of vigilantes known informally as “The Boys” set out to take down corrupt superheroes with no more than blue-collar grit and a willingness to fight dirty.",
					"poster_path": "/mY7SeH4HFFxW1hiI6cWuwCRKptN.jpg"
				},
				{
					"vote_count": 1624,
					"id": 80035,
					"video": false,
					"media_type": "movie",
					"vote_average": 5.5,
					"title": "The Watch",
					"release_date": "2012-07-26",
					"original_language": "en",
					"original_title": "The Watch",
					"genre_ids": [28, 35, 878, 9648],
					"backdrop_path": "/1I8fB7ZEaHMf9tX3tAM7JrU5k3y.jpg",
					"adult": false,
					"overview": "Four everyday suburban guys come together as an excuse to escape their humdrum lives one night a week. But when they accidentally discover that their town has become overrun with aliens posing as ordinary suburbanites, they have no choice but to save their neighborhood - and the world - from total extermination.",
					"poster_path": "/gwfgYA9wGpV4QLB0LrcexwfwC19.jpg"
				}
			],
			"gender": 1
		},
		{
			"popularity": 54.637,
			"known_for_department": "Acting",
			"name": "Henry Cavill",
			"id": 73968,
			"profile_path": "/hErUwonrQgY5Y7RfxOfv8Fq11MB.jpg",
			"adult": false,
			"known_for": [
				{
					"poster_path": "/5UsK3grJvtQrtzEgqNlDljJW96w.jpg",
					"vote_count": 13867,
					"video": false,
					"media_type": "movie",
					"id": 209112,
					"adult": false,
					"backdrop_path": "/doiUtOHzcxXFl0GVQ2n8Ay6Pirx.jpg",
					"original_language": "en",
					"original_title": "Batman v Superman: Dawn of Justice",
					"genre_ids": [28, 12, 14],
					"title": "Batman v Superman: Dawn of Justice",
					"vote_average": 5.9,
					"overview": "Fearing the actions of a god-like Super Hero left unchecked, Gotham City’s own formidable, forceful vigilante takes on Metropolis’s most revered, modern-day savior, while the world wrestles with what sort of hero it really needs. And with Batman and Superman at war with one another, a new threat quickly arises, putting mankind in greater danger than it’s ever known before.",
					"release_date": "2016-03-23"
				},
				{
					"poster_path": "/7rIPjn5TUK04O25ZkMyHrGNPgLx.jpg",
					"vote_count": 11382,
					"video": false,
					"media_type": "movie",
					"id": 49521,
					"adult": false,
					"backdrop_path": "/69EFgWWPFWbRNHmQgYdSnyJ94Ge.jpg",
					"original_language": "en",
					"original_title": "Man of Steel",
					"genre_ids": [28, 12, 14, 878],
					"title": "Man of Steel",
					"vote_average": 6.5,
					"overview": "A young boy learns that he has extraordinary powers and is not of this earth. As a young man, he journeys to discover where he came from and what he was sent here to do. But the hero in him must emerge if he is to save the world from annihilation and become the symbol of hope for all mankind.",
					"release_date": "2013-06-12"
				},
				{
					"poster_path": "/eifGNCSDuxJeS1loAXil5bIGgvC.jpg",
					"vote_count": 9635,
					"video": false,
					"media_type": "movie",
					"id": 141052,
					"adult": false,
					"backdrop_path": "/jorgjEk6a0bed6jdR5wu4S6ZvRm.jpg",
					"original_language": "en",
					"original_title": "Justice League",
					"genre_ids": [28, 12, 14, 878],
					"title": "Justice League",
					"vote_average": 6.2,
					"overview": "Fuelled by his restored faith in humanity and inspired by Superman's selfless act, Bruce Wayne and Diana Prince assemble a team of metahumans consisting of Barry Allen, Arthur Curry and Victor Stone to face the catastrophic threat of Steppenwolf and the Parademons who are on the hunt for three Mother Boxes on Earth.",
					"release_date": "2017-11-15"
				}
			],
			"gender": 2
		},
		{
			"popularity": 51.493,
			"known_for_department": "Acting",
			"name": "Millie Bobby Brown",
			"id": 1356210,
			"profile_path": "/yzfxLMcBMusKzZp9f1Z9Ags8WML.jpg",
			"adult": false,
			"known_for": [
				{
					"original_name": "Stranger Things",
					"genre_ids": [18, 9648, 10765],
					"media_type": "tv",
					"name": "Stranger Things",
					"origin_country": ["US"],
					"vote_count": 5694,
					"first_air_date": "2016-07-15",
					"backdrop_path": "/56v2KjBlU4XaOv9rVYEQypROD7P.jpg",
					"original_language": "en",
					"id": 66732,
					"vote_average": 8.5,
					"overview": "When a young boy vanishes, a small town uncovers a mystery involving secret experiments, terrifying supernatural forces, and one strange little girl.",
					"poster_path": "/x2LSRK2Cm7MZhjluni1msVJ3wDF.jpg"
				},
				{
					"original_name": "Grey's Anatomy",
					"genre_ids": [18],
					"media_type": "tv",
					"name": "Grey's Anatomy",
					"origin_country": ["US"],
					"vote_count": 3594,
					"first_air_date": "2005-03-27",
					"backdrop_path": "/edmk8xjGBsYVIf4QtLY9WMaMcXZ.jpg",
					"original_language": "en",
					"id": 1416,
					"vote_average": 8,
					"overview": "Follows the personal and professional lives of a group of doctors at Seattle’s Grey Sloan Memorial Hospital.",
					"poster_path": "/jnsvc7gCKocXnrTXF6p03cICTWb.jpg"
				},
				{
					"poster_path": "/pU3bnutJU91u3b4IeRPQTOP8jhV.jpg",
					"vote_count": 2950,
					"video": false,
					"media_type": "movie",
					"id": 373571,
					"adult": false,
					"backdrop_path": "/jb6Ju38HmKX0bYHCmAxs8HyNeJ2.jpg",
					"original_language": "en",
					"original_title": "Godzilla: King of the Monsters",
					"genre_ids": [28, 878],
					"title": "Godzilla: King of the Monsters",
					"vote_average": 6.4,
					"overview": "Follows the heroic efforts of the crypto-zoological agency Monarch as its members face off against a battery of god-sized monsters, including the mighty Godzilla, who collides with Mothra, Rodan, and his ultimate nemesis, the three-headed King Ghidorah. When these ancient super-species, thought to be mere myths, rise again, they all vie for supremacy, leaving humanity's very existence hanging in the balance.",
					"release_date": "2019-05-29"
				}
			],
			"gender": 1
		},
		{
			"popularity": 49.234,
			"known_for_department": "Acting",
			"gender": 1,
			"id": 223461,
			"profile_path": "/1zev3EB3bQ3yFbUAKuv3Alh34Fh.jpg",
			"adult": false,
			"known_for": [
				{
					"release_date": "2007-09-14",
					"vote_count": 146,
					"video": false,
					"media_type": "movie",
					"id": 14753,
					"vote_average": 5.7,
					"title": "Silk",
					"original_language": "en",
					"original_title": "Silk",
					"genre_ids": [18, 10749],
					"adult": false,
					"overview": "Based on the best-selling novel by Alessandro Baricco, this visually stunning film tells the story of a French trader who finds unexpected love far away from home.",
					"poster_path": "/wbOxRN7bqZ0f10WOyeYe6d0OUJe.jpg"
				},
				{
					"original_name": "仮面ライダ",
					"vote_count": 45,
					"media_type": "tv",
					"poster_path": "/o57T19zgZakEpre3d9ddy1UZonp.jpg",
					"name": "Kamen Rider",
					"first_air_date": "1971-04-03",
					"id": 2661,
					"original_language": "ja",
					"genre_ids": [18, 10759, 10765],
					"vote_average": 4.9,
					"overview": "A Japanese anthology series centered around a man who transforms into a bug-themed superhero.",
					"origin_country": ["JP"]
				},
				{
					"release_date": "2017-02-01",
					"id": 474647,
					"vote_count": 24,
					"video": false,
					"media_type": "movie",
					"vote_average": 7.4,
					"title": "Impossibility Defense",
					"genre_ids": [9648, 53],
					"original_title": "不能犯",
					"original_language": "ja",
					"adult": false,
					"backdrop_path": "/lnK7YmK4cwEdqW5cEDk2FauInc2.jpg",
					"overview": "At a certain park, there is a mysterious man, who has red eyes and a black suit, that people can go to and request him to kill someone. His assassinations can never be blamed on him because he takes no illegal action. His strength is in the power of suggestion and the arrangement of events. He accepts these requests, all the while privately mocking the foolishness of those whose unwise wishes he grants.",
					"poster_path": "/dEsK36fG7VGf6HNU9wVTxqP9nKa.jpg"
				}
			],
			"name": "Sei Ashina"
		},
		{
			"popularity": 48.679,
			"known_for_department": "Acting",
			"name": "Tessa Hoder",
			"id": 2263933,
			"profile_path": "/oBfjVOzILe9OnYOl3kuIl698GNY.jpg",
			"adult": false,
			"known_for": [
				{
					"poster_path": "/uWC8vrvERAjKu7ecT1Tuu6ohKSh.jpg",
					"vote_count": 7,
					"video": false,
					"media_type": "movie",
					"id": 571683,
					"adult": false,
					"backdrop_path": "/zgl7RIABM0HybST6frkyC47pGQO.jpg",
					"original_language": "da",
					"original_title": "Selvhenter",
					"genre_ids": [35],
					"title": "Heavy Load",
					"vote_average": 6.6,
					"overview": "The two estranged brothers Emil and Magnus travel to Spain to bring home the body of their drunken and now dead father. What Emil doesn’t know is that Magnus has only agreed to go because of their father’s valuable Rolex watch which can save his bleeding finances. But when it turns out the transportation of the body will cost more than 10,000 Euro, Magnus convinces his reluctant little brother to run away with the body hidden in a roof box on top of a way too small rental car. Soon the two brothers find themselves on a wild escape from the police, and their father’s last trip forces them to face their own problems.",
					"release_date": "2019-03-07"
				},
				{
					"original_name": "Den som dræber - Fanget af mørket",
					"id": 87542,
					"media_type": "tv",
					"name": "Darkness: Those Who Kill",
					"vote_count": 7,
					"vote_average": 8.6,
					"first_air_date": "2019-02-22",
					"poster_path": "/6bstsCJ5JdAZ38nhmhv5dwzjibm.jpg",
					"genre_ids": [80],
					"original_language": "da",
					"backdrop_path": "/fUjCQnmMFP6rtEAmBcx3dFiMNDf.jpg",
					"overview": "Investigator Jan and profiler Louise constantly move around in the thrilling periphery of a murderer's view as they link a series of killings.",
					"origin_country": ["DK"]
				},
				{
					"original_name": "Ondt i Røven",
					"id": 87545,
					"media_type": "tv",
					"name": "Ondt i Røven",
					"vote_count": 0,
					"vote_average": 0,
					"first_air_date": "2019-02-04",
					"poster_path": "/dL56ODSZEv4YyD08K24W1UukNBV.jpg",
					"genre_ids": [18],
					"original_language": "da",
					"backdrop_path": "/kusfD6xOPmSLTqPArNLbKZLhVxk.jpg",
					"overview": "Tessa is enthralled by the Copenhagen queer community, after she moves onto a couch in the collective \"The soft core\". Here a new world opens to Tessa, who begins questioning herself and her life, while she eagerly struggles to fit in. It turns out not being too easy; in the queer community she looks too straight, is too privileged and ignorant, but among her hetero friends she's too queer. Sometimes you have find your community to find yourself.",
					"origin_country": []
				}
			],
			"gender": 1
		},
		{
			"popularity": 46.921,
			"known_for_department": "Acting",
			"gender": 1,
			"id": 1245,
			"profile_path": "/6NsMbJXRlDZuDzatN2akFdGuTvx.jpg",
			"adult": false,
			"known_for": [
				{
					"release_date": "2012-04-25",
					"id": 24428,
					"vote_count": 23194,
					"video": false,
					"media_type": "movie",
					"vote_average": 7.7,
					"title": "The Avengers",
					"genre_ids": [28, 12, 878],
					"original_title": "The Avengers",
					"original_language": "en",
					"adult": false,
					"backdrop_path": "/kwUQFeFXOOpgloMgZaadhzkbTI4.jpg",
					"overview": "When an unexpected enemy emerges and threatens global safety and security, Nick Fury, director of the international peacekeeping agency known as S.H.I.E.L.D., finds himself in need of a team to pull the world back from the brink of disaster. Spanning the globe, a daring recruitment effort begins!",
					"poster_path": "/RYMX2wcKCBAr24UyPD7xwmjaTn.jpg"
				},
				{
					"release_date": "2018-04-25",
					"id": 299536,
					"vote_count": 19774,
					"video": false,
					"media_type": "movie",
					"vote_average": 8.3,
					"title": "Avengers: Infinity War",
					"genre_ids": [28, 12, 878],
					"original_title": "Avengers: Infinity War",
					"original_language": "en",
					"adult": false,
					"backdrop_path": "/lmZFxXgJE3vgrciwuDib0N8CfQo.jpg",
					"overview": "As the Avengers and their allies have continued to protect the world from threats too large for any one hero to handle, a new danger has emerged from the cosmic shadows: Thanos. A despot of intergalactic infamy, his goal is to collect all six Infinity Stones, artifacts of unimaginable power, and use them to inflict his twisted will on all of reality. Everything the Avengers have fought for has led up to this moment - the fate of Earth and existence itself has never been more uncertain.",
					"poster_path": "/7WsyChQLEftFiDOVTGkv3hFpyyt.jpg"
				},
				{
					"release_date": "2016-04-27",
					"id": 271110,
					"vote_count": 16855,
					"video": false,
					"media_type": "movie",
					"vote_average": 7.4,
					"title": "Captain America: Civil War",
					"genre_ids": [28, 12, 878],
					"original_title": "Captain America: Civil War",
					"original_language": "en",
					"adult": false,
					"backdrop_path": "/7FWlcZq3r6525LWOcvO9kNWurN1.jpg",
					"overview": "Following the events of Age of Ultron, the collective governments of the world pass an act designed to regulate all superhuman activity. This polarizes opinion amongst the Avengers, causing two factions to side with Iron Man or Captain America, which causes an epic battle between former allies.",
					"poster_path": "/rAGiXaUfPzY7CDEyNKUofk3Kw2e.jpg"
				}
			],
			"name": "Scarlett Johansson"
		},
		{
			"popularity": 42.629,
			"known_for_department": "Acting",
			"gender": 1,
			"id": 109513,
			"profile_path": "/lh5zibQXYH1MNqkuX8TmxyNYHhK.jpg",
			"adult": false,
			"known_for": [
				{
					"poster_path": "/2Gfjn962aaFSD6eST6QU3oLDZTo.jpg",
					"id": 254128,
					"vote_count": 6148,
					"video": false,
					"media_type": "movie",
					"adult": false,
					"backdrop_path": "/xYRUnZvUOrAhCw8CrBSLtbVVwNl.jpg",
					"genre_ids": [28, 18, 53],
					"original_title": "San Andreas",
					"original_language": "en",
					"title": "San Andreas",
					"vote_average": 6.2,
					"overview": "In the aftermath of a massive earthquake in California, a rescue-chopper pilot makes a dangerous journey across the state in order to rescue his estranged daughter.",
					"release_date": "2015-05-27"
				},
				{
					"release_date": "2017-05-12",
					"id": 339846,
					"vote_count": 5947,
					"video": false,
					"media_type": "movie",
					"vote_average": 6.1,
					"title": "Baywatch",
					"genre_ids": [28, 35],
					"original_title": "Baywatch",
					"original_language": "en",
					"adult": false,
					"backdrop_path": "/6QmX2BDVr1hIOIPHqnxvp1C1ZZp.jpg",
					"overview": "Devoted lifeguard Mitch Buchannon butts heads with a brash new recruit. Together, they uncover a local criminal plot that threatens the future of the Bay.",
					"poster_path": "/6HE4xd8zloDqmjMZuhUCCw2UcY1.jpg"
				},
				{
					"release_date": "2010-02-01",
					"id": 32657,
					"vote_count": 5387,
					"video": false,
					"media_type": "movie",
					"vote_average": 6.2,
					"title": "Percy Jackson & the Olympians: The Lightning Thief",
					"genre_ids": [12, 14, 10751],
					"original_title": "Percy Jackson & the Olympians: The Lightning Thief",
					"original_language": "en",
					"adult": false,
					"backdrop_path": "/sEyNWq9985lyUrwayWnvicT4FHA.jpg",
					"overview": "Accident prone teenager, Percy discovers he's actually a demi-God, the son of Poseidon, and he is needed when Zeus' lightning is stolen. Percy must master his new found skills in order to prevent a war between the Gods that could devastate the entire world.",
					"poster_path": "/brzpTyZ5bnM7s53C1KSk1TmrMO6.jpg"
				}
			],
			"name": "Alexandra Daddario"
		},
		{
			"popularity": 39.16,
			"known_for_department": "Acting",
			"name": "Dwayne Johnson",
			"id": 18918,
			"profile_path": "/cgoy7t5Ve075naBPcewZrc08qGw.jpg",
			"adult": false,
			"known_for": [
				{
					"poster_path": "/22hqf97LadMvkd4zDi3Bq25xSqD.jpg",
					"vote_count": 9789,
					"video": false,
					"media_type": "movie",
					"id": 353486,
					"adult": false,
					"backdrop_path": "/rz3TAyd5kmiJmozp3GUbYeB5Kep.jpg",
					"original_language": "en",
					"original_title": "Jumanji: Welcome to the Jungle",
					"genre_ids": [28, 12, 35, 14],
					"title": "Jumanji: Welcome to the Jungle",
					"vote_average": 6.8,
					"overview": "The tables are turned as four teenagers are sucked into Jumanji's world - pitted against rhinos, black mambas and an endless variety of jungle traps and puzzles. To survive, they'll play as characters from the game.",
					"release_date": "2017-12-09"
				},
				{
					"poster_path": "/4JeejGugONWpJkbnvL12hVoYEDa.jpg",
					"vote_count": 8702,
					"video": false,
					"media_type": "movie",
					"id": 277834,
					"adult": false,
					"backdrop_path": "/oWU6dgu3RgdSZElkhbZuoPtkWAJ.jpg",
					"original_language": "en",
					"original_title": "Moana",
					"genre_ids": [12, 16, 35, 10751],
					"title": "Moana",
					"vote_average": 7.6,
					"overview": "In Ancient Polynesia, when a terrible curse incurred by Maui reaches an impetuous Chieftain's daughter's island, she answers the Ocean's call to seek out the demigod to set things right.",
					"release_date": "2016-11-23"
				},
				{
					"vote_count": 8134,
					"id": 82992,
					"video": false,
					"media_type": "movie",
					"vote_average": 6.8,
					"title": "Fast & Furious 6",
					"release_date": "2013-05-21",
					"original_language": "en",
					"original_title": "Fast & Furious 6",
					"genre_ids": [28, 53, 80],
					"backdrop_path": "/mRfI3y2oAd7ejur2di09xC9niqp.jpg",
					"adult": false,
					"overview": "Hobbs has Dominic and Brian reassemble their crew to take down a team of mercenaries: Dominic unexpectedly gets convoluted also facing his presumed deceased girlfriend, Letty.",
					"poster_path": "/n31VRDodbaZxkrZmmzyYSFNVpW5.jpg"
				}
			],
			"gender": 2
		},
		{
			"popularity": 39.031,
			"known_for_department": "Acting",
			"name": "Peyton List",
			"id": 1254435,
			"profile_path": "/5p8KwRgBUYVcKBKTYFdD30o6dAc.jpg",
			"adult": false,
			"known_for": [
				{
					"poster_path": "/olxpyq9kJAZ2NU1siLshhhXEPR7.jpg",
					"vote_count": 10014,
					"video": false,
					"media_type": "movie",
					"id": 558,
					"adult": false,
					"backdrop_path": "/6al048Lat3eLVQOuKtc9h6Tu94d.jpg",
					"original_language": "en",
					"original_title": "Spider-Man 2",
					"genre_ids": [28, 12, 14],
					"title": "Spider-Man 2",
					"vote_average": 7.1,
					"overview": "Peter Parker is going through a major identity crisis. Burned out from being Spider-Man, he decides to shelve his superhero alter ego, which leaves the city suffering in the wake of carnage left by the evil Doc Ock. In the meantime, Parker still can't act on his feelings for Mary Jane Watson, a girl he's loved since childhood.",
					"release_date": "2004-06-25"
				},
				{
					"vote_count": 3638,
					"id": 27022,
					"video": false,
					"media_type": "movie",
					"vote_average": 6,
					"title": "The Sorcerer's Apprentice",
					"release_date": "2010-07-13",
					"original_language": "en",
					"original_title": "The Sorcerer's Apprentice",
					"genre_ids": [14, 12, 28],
					"backdrop_path": "/8ESiTGI9gk8f33Yn9sltEFqyxlj.jpg",
					"adult": false,
					"overview": "Balthazar Blake is a master sorcerer in modern-day Manhattan trying to defend the city from his arch-nemesis, Maxim Horvath. Balthazar can't do it alone, so he recruits Dave Stutler, a seemingly average guy who demonstrates hidden potential, as his reluctant protégé. The sorcerer gives his unwilling accomplice a crash course in the art and science of magic, and together, these unlikely partners work to stop the forces of darkness.",
					"poster_path": "/b5pIUsGll0418NyfNA5eYCI9aoK.jpg"
				},
				{
					"poster_path": "/j7umuMiLCHvWT7wYhFKJOTFSokF.jpg",
					"vote_count": 2706,
					"video": false,
					"media_type": "movie",
					"id": 23169,
					"adult": false,
					"backdrop_path": "/noOfZIEWjLX2tbwtujAU3H2tQaV.jpg",
					"original_language": "en",
					"original_title": "Remember Me",
					"genre_ids": [18, 10749],
					"title": "Remember Me",
					"vote_average": 7.1,
					"overview": "Still reeling from a heartbreaking family event and his parents' subsequent divorce, Tyler Hawkins discovers a fresh lease on life when he meets Ally Craig, a gregarious beauty who witnessed her mother's death. But as the couple draws closer, the fallout from their separate tragedies jeopardizes their love.",
					"release_date": "2010-03-12"
				}
			],
			"gender": 1
		},
		{
			"popularity": 37.823,
			"known_for_department": "Acting",
			"name": "Tom Cruise",
			"id": 500,
			"profile_path": "/s9QuHNTJf8P8xTtw3JcaKJMa3uo.jpg",
			"adult": false,
			"known_for": [
				{
					"poster_path": "/uUHvlkLavotfGsNtosDy8ShsIYF.jpg",
					"vote_count": 9858,
					"video": false,
					"media_type": "movie",
					"id": 137113,
					"adult": false,
					"backdrop_path": "/auZIuHEUec5tBTns3tCRXfayxZq.jpg",
					"original_language": "en",
					"original_title": "Edge of Tomorrow",
					"genre_ids": [28, 878],
					"title": "Edge of Tomorrow",
					"vote_average": 7.6,
					"overview": "Major Bill Cage is an officer who has never seen a day of combat when he is unceremoniously demoted and dropped into combat. Cage is killed within minutes, managing to take an alpha alien down with him. He awakens back at the beginning of the same day and is forced to fight and die again... and again - as physical contact with the alien has thrown him into a time loop.",
					"release_date": "2014-05-27"
				},
				{
					"vote_count": 8067,
					"id": 75612,
					"video": false,
					"media_type": "movie",
					"vote_average": 6.6,
					"title": "Oblivion",
					"release_date": "2013-04-10",
					"original_language": "en",
					"original_title": "Oblivion",
					"genre_ids": [28, 878, 12, 9648],
					"backdrop_path": "/Pv6vu1lxgct3GWhUXVVOMZwNlZ.jpg",
					"adult": false,
					"overview": "Jack Harper is one of the last few drone repairmen stationed on Earth.  Part of a massive operation to extract vital resources after decades of war with a terrifying threat known as the Scavs, Jack’s mission is nearly complete.  His existence is brought crashing down when he rescues a beautiful  stranger from a downed spacecraft.  Her arrival triggers a chain of events that  forces him to question everything he knows and puts the fate of humanity in his hands.",
					"poster_path": "/2ncs7hqBsEjFMqt6Y7ShBCO9tWs.jpg"
				},
				{
					"poster_path": "/7GCKNRbzcA4rJXAKoE8KS9IDnZP.jpg",
					"vote_count": 7212,
					"video": false,
					"media_type": "movie",
					"id": 56292,
					"adult": false,
					"backdrop_path": "/hqyjzDRCs1N5gEsh2gklzPdsEFD.jpg",
					"original_language": "en",
					"original_title": "Mission: Impossible - Ghost Protocol",
					"genre_ids": [28, 12, 53],
					"title": "Mission: Impossible - Ghost Protocol",
					"vote_average": 7,
					"overview": "Ethan Hunt and his team are racing against time to track down a dangerous terrorist named Hendricks, who has gained access to Russian nuclear launch codes and is planning a strike on the United States. An attempt to stop him ends in an explosion causing severe destruction to the Kremlin and the IMF to be implicated in the bombing, forcing the President to disavow them. No longer being aided by the government, Ethan and his team chase Hendricks around the globe, although they might still be too late to stop a disaster.",
					"release_date": "2011-12-07"
				}
			],
			"gender": 2
		},
		{
			"popularity": 36.806,
			"known_for_department": "Acting",
			"gender": 1,
			"id": 122503,
			"profile_path": "/cL6JccAYqiZQEAIEFObEUC9LTt7.jpg",
			"adult": false,
			"known_for": [
				{
					"release_date": "2020-09-04",
					"id": 337401,
					"vote_count": 2101,
					"video": false,
					"media_type": "movie",
					"vote_average": 7.4,
					"title": "Mulan",
					"genre_ids": [28, 12, 18, 14],
					"original_title": "Mulan",
					"original_language": "en",
					"adult": false,
					"backdrop_path": "/zzWGRw277MNoCs3zhyG3YmYQsXv.jpg",
					"overview": "When the Emperor of China issues a decree that one man per family must serve in the Imperial Chinese Army to defend the country from Huns, Hua Mulan, the eldest daughter of an honored warrior, steps in to take the place of her ailing father. She is spirited, determined and quick on her feet. Disguised as a man by the name of Hua Jun, she is tested every step of the way and must harness her innermost strength and embrace her true potential.",
					"poster_path": "/aKx1ARwG55zZ0GpRvU2WrGrCG9o.jpg"
				},
				{
					"release_date": "2008-04-18",
					"id": 1729,
					"vote_count": 1051,
					"video": false,
					"media_type": "movie",
					"vote_average": 6.5,
					"title": "The Forbidden Kingdom",
					"genre_ids": [28, 12, 14],
					"original_title": "The Forbidden Kingdom",
					"original_language": "en",
					"adult": false,
					"backdrop_path": "/aNKhC2nzGr3kAggKubJ56MbFOUc.jpg",
					"overview": "An American teenager who is obsessed with Hong Kong cinema and kung-fu classics makes an extraordinary discovery in a Chinatown pawnshop: the legendary stick weapon of the Chinese sage and warrior, the Monkey King. With the lost relic in hand, the teenager unexpectedly finds himself travelling back to ancient China to join a crew of warriors from martial arts lore on a dangerous quest to free the imprisoned Monkey King.",
					"poster_path": "/mkrwLBAFHwLnQF8qdhCH0VOQqff.jpg"
				},
				{
					"poster_path": "/efsgCTlofzIuysfokEp7hwQnUho.jpg",
					"id": 289720,
					"vote_count": 293,
					"video": false,
					"media_type": "movie",
					"adult": false,
					"backdrop_path": "/sETF4vyjb0FonUJVqgrkaPWqiIf.jpg",
					"genre_ids": [28],
					"original_title": "Outcast",
					"original_language": "en",
					"title": "Outcast",
					"vote_average": 4.8,
					"overview": "A mysterious warrior teams up with the daughter and son of a deposed Chinese Emperor to defeat their cruel Uncle, who seeks their deaths.",
					"release_date": "2014-09-26"
				}
			],
			"name": "Liu Yifei"
		},
		{
			"popularity": 33.479,
			"known_for_department": "Acting",
			"name": "Aidan Gallagher",
			"id": 1520843,
			"profile_path": "/zwOMopF4dAAvA6Lexr2dxJ9qBlD.jpg",
			"adult": false,
			"known_for": [
				{
					"original_name": "The Umbrella Academy",
					"genre_ids": [35, 18, 10759, 10765],
					"media_type": "tv",
					"name": "The Umbrella Academy",
					"origin_country": ["US"],
					"vote_count": 2058,
					"first_air_date": "2019-02-15",
					"backdrop_path": "/qJxzjUjCpTPvDHldNnlbRC4OqEh.jpg",
					"original_language": "en",
					"id": 75006,
					"vote_average": 8.6,
					"overview": "A dysfunctional family of superheroes comes together to solve the mystery of their father's death, the threat of the apocalypse and more.",
					"poster_path": "/scZlQQYnDVlnpxFTxaIv2g0BWnL.jpg"
				},
				{
					"original_name": "Nicky, Ricky, Dicky & Dawn",
					"id": 61854,
					"media_type": "tv",
					"name": "Nicky, Ricky, Dicky & Dawn",
					"vote_count": 28,
					"vote_average": 7.8,
					"first_air_date": "2014-09-13",
					"poster_path": "/mIp7OThxhHgPya3p0SW8QNEPCzv.jpg",
					"genre_ids": [],
					"original_language": "en",
					"backdrop_path": "/bLfG0KPMpCUg2yKpKVVB5e2vKJA.jpg",
					"overview": "The story of a 10-year-old girl Dawn Haley whose sibling rivalry with her three brothers is heightened by the fact that they are quadruplets.",
					"origin_country": ["US"]
				},
				{
					"poster_path": "/tzp6yNIrOva50RPNlJxJ3T2ZV02.jpg",
					"vote_count": 22,
					"video": false,
					"media_type": "movie",
					"id": 458621,
					"adult": false,
					"backdrop_path": null,
					"original_language": "en",
					"original_title": "Nickelodeon's Sizzling Summer Camp Special",
					"genre_ids": [],
					"title": "Nickelodeon's Sizzling Summer Camp Special",
					"vote_average": 5.5,
					"overview": "Nickelodeon’s Sizzling Summer Camp Special features all of your favorite Nickelodeon stars as they head off to a sleep-away camp together — but they soon find themselves in danger! The friends find out that their campsite has been haunted. The mysterious and legendary creatures have been haunting the camp for years!  This is the third Nickelodeon Special in the series starring Nickelodeon stars such as Lizzy Greene, Jack Griffo, Kyla Drew Simmons, Jade Pettyjohn, Casey Simpson, and Mace Coronel.",
					"release_date": "2017-06-04"
				}
			],
			"gender": 2
		},
		{
			"popularity": 32.336,
			"known_for_department": "Acting",
			"gender": 1,
			"id": 1522703,
			"profile_path": "/ctha5vTjjFF3Z71e8WNFFMPbkoz.jpg",
			"adult": false,
			"known_for": [
				{
					"original_name": "Güneşin Kızları",
					"id": 64164,
					"origin_country": ["TR"],
					"name": "Sun's Daughters",
					"backdrop_path": "/vKV0XxFTWJDdzL39Dddp4uLri0A.jpg",
					"original_language": "tr",
					"first_air_date": "2015-06-18",
					"genre_ids": [18],
					"vote_count": 29,
					"media_type": "tv",
					"vote_average": 7.2,
					"overview": "A teacher and a mother of three teenage daughters , gunes agrees to move from her home city Izmir to Istanbul to be with mysterious wealthy man who has fallen for her. Gunesin kizlari follows the never ending drama of Güneş and her daughters they face the events of their newly transformed lives.",
					"poster_path": "/kVJbUlcWGyLp0H1xXLo1OicmU8x.jpg"
				},
				{
					"original_name": "Halka",
					"id": 85545,
					"origin_country": ["TR"],
					"name": "Halka",
					"backdrop_path": "/8QxaBXr5ZpvZVEEMldltipyXZEK.jpg",
					"original_language": "tr",
					"first_air_date": "2019-01-15",
					"genre_ids": [10759, 18, 80],
					"vote_count": 3,
					"media_type": "tv",
					"vote_average": 8.7,
					"overview": "",
					"poster_path": "/opU1LKrieFYItAgMB5YL00UUqYY.jpg"
				},
				{
					"original_name": "Aşk Laftan Anlamaz",
					"id": 67570,
					"origin_country": ["TR"],
					"name": "Aşk Laftan Anlamaz",
					"backdrop_path": "/vuCaETmmxdLATM5BO3saN8FAKeB.jpg",
					"original_language": "tr",
					"first_air_date": "2016-06-15",
					"genre_ids": [35, 18],
					"vote_count": 3,
					"media_type": "tv",
					"vote_average": 8.3,
					"overview": "Hayat is a country girl with strict parents. She is in a love hate relationship with her boss Murat. Hayat is full of secrets that can ruin her career and relationship.",
					"poster_path": "/tnyM86EpqVRTHZKQenaUrbsTAGG.jpg"
				}
			],
			"name": "Hande Erçel"
		},
		{
			"popularity": 32.299,
			"known_for_department": "Acting",
			"gender": 2,
			"id": 1946699,
			"profile_path": "/kR7cSIIXQNugXHYjcPwp30uXHg7.jpg",
			"adult": false,
			"known_for": [
				{
					"original_name": "Arrow",
					"vote_count": 3970,
					"poster_path": "/gKG5QGz5Ngf8fgWpBsWtlg5L2SF.jpg",
					"media_type": "tv",
					"name": "Arrow",
					"vote_average": 6.4,
					"id": 1412,
					"first_air_date": "2012-10-10",
					"original_language": "en",
					"genre_ids": [80, 18, 9648, 10759],
					"backdrop_path": "/fFT7T9y9NVRdcdVh81roVrJBcDh.jpg",
					"overview": "Spoiled billionaire playboy Oliver Queen is missing and presumed dead when his yacht is lost at sea. He returns five years later a changed man, determined to clean up the city as a hooded vigilante armed with a bow.",
					"origin_country": ["US"]
				},
				{
					"original_name": "Medici: Masters of Florence",
					"vote_count": 81,
					"poster_path": "/vFtsI6Nk3cy2l4LGoh1aFRZKaQ7.jpg",
					"media_type": "tv",
					"name": "Medici: Masters of Florence",
					"vote_average": 7.5,
					"id": 66761,
					"first_air_date": "2016-10-18",
					"original_language": "en",
					"genre_ids": [18, 10768],
					"backdrop_path": "/oeCoI91iFnUzmrjVi3f9yuA093m.jpg",
					"overview": "The story of the Medici family of Florence, their ascent from simple merchants to power brokers sparking an economic and cultural revolution. Along the way, they also accrue a long list of powerful enemies.",
					"origin_country": ["IT", "GB"]
				},
				{
					"original_name": "Neighbours",
					"vote_count": 20,
					"poster_path": "/qwDeDAF1ACwffkpxY8bCZo1pjdj.jpg",
					"media_type": "tv",
					"name": "Neighbours",
					"vote_average": 6.3,
					"id": 2674,
					"first_air_date": "1985-03-18",
					"original_language": "en",
					"genre_ids": [10766],
					"backdrop_path": "/ve02nkLrrjFPy8vfklcU6TpJRTI.jpg",
					"overview": "Neighbours is an Australian television soap opera.  The show's storylines concern the domestic and professional lives of the people who live and work in Erinsborough, a fictional suburb of Melbourne, Victoria. The series primarily centres around the residents of Ramsay Street, a short cul-de-sac, and its neighbouring areas, the Lassiters complex, which includes a bar, hotel, cafe, news office and park. Neighbours began with three families created by Watson – the Ramsays, the Robinsons and the Clarkes. Watson said that he wanted to show three families who are friends living in a small street. The Robinsons and the Ramsays had a long history and were involved in an ongoing rivalry.",
					"origin_country": ["AU"]
				}
			],
			"name": "William Franklyn-Miller"
		},
		{
			"popularity": 31.577,
			"known_for_department": "Acting",
			"gender": 2,
			"id": 2524,
			"profile_path": "/yVGF9FvDxTDPhGimTbZNfghpllA.jpg",
			"adult": false,
			"known_for": [
				{
					"release_date": "2010-07-15",
					"id": 27205,
					"vote_count": 27251,
					"video": false,
					"media_type": "movie",
					"vote_average": 8.3,
					"title": "Inception",
					"genre_ids": [28, 12, 878],
					"original_title": "Inception",
					"original_language": "en",
					"adult": false,
					"backdrop_path": "/s3TBrRGB1iav7gFOCNx3H31MoES.jpg",
					"overview": "Cobb, a skilled thief who commits corporate espionage by infiltrating the subconscious of his targets is offered a chance to regain his old life as payment for a task considered to be impossible: \"inception\", the implantation of another person's idea into a target's subconscious.",
					"poster_path": "/9gk7adHYeDvHkCSEqAvQNLV5Uge.jpg"
				},
				{
					"release_date": "2015-05-13",
					"id": 76341,
					"vote_count": 17017,
					"video": false,
					"media_type": "movie",
					"vote_average": 7.5,
					"title": "Mad Max: Fury Road",
					"genre_ids": [28, 12, 878],
					"original_title": "Mad Max: Fury Road",
					"original_language": "en",
					"adult": false,
					"backdrop_path": "/nlCHUWjY9XWbuEUQauCBgnY8ymF.jpg",
					"overview": "An apocalyptic story set in the furthest reaches of our planet, in a stark desert landscape where humanity is broken, and most everyone is crazed fighting for the necessities of life. Within this world exist two rebels on the run who just might be able to restore order.",
					"poster_path": "/8tZYtuWezp8JbcsvHYO0O46tFbo.jpg"
				},
				{
					"release_date": "2012-07-16",
					"id": 49026,
					"vote_count": 16691,
					"video": false,
					"media_type": "movie",
					"vote_average": 7.7,
					"title": "The Dark Knight Rises",
					"genre_ids": [28, 80, 18, 53],
					"original_title": "The Dark Knight Rises",
					"original_language": "en",
					"adult": false,
					"backdrop_path": "/yzsegNpkRCPadnWmshrJzT3ardR.jpg",
					"overview": "Following the death of District Attorney Harvey Dent, Batman assumes responsibility for Dent's crimes to protect the late attorney's reputation and is subsequently hunted by the Gotham City Police Department. Eight years later, Batman encounters the mysterious Selina Kyle and the villainous Bane, a new terrorist leader who overwhelms Gotham's finest. The Dark Knight resurfaces to protect a city that has branded him an enemy.",
					"poster_path": "/vzvKcPQ4o7TjWeGIn0aGC9FeVNu.jpg"
				}
			],
			"name": "Tom Hardy"
		},
		{
			"popularity": 31.084,
			"known_for_department": "Acting",
			"gender": 2,
			"id": 85,
			"profile_path": "/532tIC5wzmmR1jO7oA83rTiLvBx.jpg",
			"adult": false,
			"known_for": [
				{
					"release_date": "2003-07-09",
					"id": 22,
					"vote_count": 15007,
					"video": false,
					"media_type": "movie",
					"vote_average": 7.7,
					"title": "Pirates of the Caribbean: The Curse of the Black Pearl",
					"genre_ids": [28, 12, 14],
					"original_title": "Pirates of the Caribbean: The Curse of the Black Pearl",
					"original_language": "en",
					"adult": false,
					"backdrop_path": "/7yxjg8pvp3JuqguUaJPYTma6Z7t.jpg",
					"overview": "Jack Sparrow, a freewheeling 18th-century pirate, quarrels with a rival pirate bent on pillaging Port Royal. When the governor's daughter is kidnapped, Sparrow decides to help the girl's love save her.",
					"poster_path": "/z8onk7LV9Mmw6zKz4hT6pzzvmvl.jpg"
				},
				{
					"release_date": "2016-11-16",
					"id": 259316,
					"vote_count": 14495,
					"video": false,
					"media_type": "movie",
					"vote_average": 7.4,
					"title": "Fantastic Beasts and Where to Find Them",
					"genre_ids": [12, 14],
					"original_title": "Fantastic Beasts and Where to Find Them",
					"original_language": "en",
					"adult": false,
					"backdrop_path": "/7GrpqAs0oDcFcwFwyygnUI7BrZA.jpg",
					"overview": "In 1926, Newt Scamander arrives at the Magical Congress of the United States of America with a magically expanded briefcase, which houses a number of dangerous creatures and their habitats. When the creatures escape from the briefcase, it sends the American wizarding authorities after Newt, and threatens to strain even further the state of magical and non-magical relations.",
					"poster_path": "/h6NYfVUyM6CDURtZSnBpz647Ldd.jpg"
				},
				{
					"release_date": "2006-06-20",
					"id": 58,
					"vote_count": 11432,
					"video": false,
					"media_type": "movie",
					"vote_average": 7.3,
					"title": "Pirates of the Caribbean: Dead Man's Chest",
					"genre_ids": [28, 12, 14],
					"original_title": "Pirates of the Caribbean: Dead Man's Chest",
					"original_language": "en",
					"adult": false,
					"backdrop_path": "/vv5a8u6e40kyH0Hp6HuamAgzRai.jpg",
					"overview": "Captain Jack Sparrow works his way out of a blood debt with the ghostly Davey Jones to avoid eternal damnation.",
					"poster_path": "/AdRQGfT05z6L9gIpUpkh4McMmpm.jpg"
				}
			],
			"name": "Johnny Depp"
		},
		{
			"popularity": 31.062,
			"known_for_department": "Acting",
			"name": "Jessica Alba",
			"id": 56731,
			"profile_path": "/kB0XNtvkOuaFjk9Z2RZIcp5Kig2.jpg",
			"adult": false,
			"known_for": [
				{
					"poster_path": "/8HLQLILZLhDQWO6JDpvY6XJLH75.jpg",
					"vote_count": 6926,
					"video": false,
					"media_type": "movie",
					"id": 9738,
					"adult": false,
					"backdrop_path": "/ePJ3OOj2lE5k7zIeOL2NBDHZhLk.jpg",
					"original_language": "en",
					"original_title": "Fantastic Four",
					"genre_ids": [28, 12, 14, 878],
					"title": "Fantastic Four",
					"vote_average": 5.7,
					"overview": "During a space voyage, four scientists are altered by cosmic rays: Reed Richards gains the ability to stretch his body; Sue Storm can become invisible; Johnny Storm controls fire; and Ben Grimm is turned into a super-strong … thing. Together, these \"Fantastic Four\" must now thwart the evil plans of Dr. Doom and save the world from certain destruction.",
					"release_date": "2005-06-29"
				},
				{
					"vote_count": 5843,
					"id": 1979,
					"video": false,
					"media_type": "movie",
					"vote_average": 5.6,
					"title": "Fantastic Four: Rise of the Silver Surfer",
					"release_date": "2007-06-13",
					"original_language": "en",
					"original_title": "Fantastic Four: Rise of the Silver Surfer",
					"genre_ids": [12, 14, 28, 53],
					"backdrop_path": "/4hPJT531skippmci5BfGrJYGfRv.jpg",
					"adult": false,
					"overview": "The Fantastic Four return to the big screen as a new and all powerful enemy threatens the Earth. The seemingly unstoppable 'Silver Surfer', but all is not what it seems and there are old and new enemies that pose a greater threat than the intrepid superheroes realize.",
					"poster_path": "/9wRfzTcMyyzkQxVDqBHv8RwuZOv.jpg"
				},
				{
					"poster_path": "/1Br0CXgpDIgF0ue7HVhO08bn7kn.jpg",
					"vote_count": 5680,
					"video": false,
					"media_type": "movie",
					"id": 187,
					"adult": false,
					"backdrop_path": "/t9kQnqiaxQ8TLB25rTzDKLd0fdM.jpg",
					"original_language": "en",
					"original_title": "Sin City",
					"genre_ids": [28, 80, 53],
					"title": "Sin City",
					"vote_average": 7.4,
					"overview": "Welcome to Sin City. This town beckons to the tough, the corrupt, the brokenhearted. Some call it dark… Hard-boiled. Then there are those who call it home — Crooked cops, sexy dames, desperate vigilantes. Some are seeking revenge, others lust after redemption, and then there are those hoping for a little of both. A universe of unlikely and reluctant heroes still trying to do the right thing in a city that refuses to care.",
					"release_date": "2005-04-01"
				}
			],
			"gender": 1
		},
		{
			"popularity": 31.044,
			"known_for_department": "Acting",
			"name": "Woody Harrelson",
			"id": 57755,
			"profile_path": "/gaibtvUFIlwHzRvNKV5UfrR4GCM.jpg",
			"adult": false,
			"known_for": [
				{
					"poster_path": "/mgZKtOvxtDX5HtUa5fAVQ5d1Afh.jpg",
					"vote_count": 16926,
					"video": false,
					"media_type": "movie",
					"id": 70160,
					"adult": false,
					"backdrop_path": "/5fgcgDUV1YZ296eitqoOnAd2laa.jpg",
					"original_language": "en",
					"original_title": "The Hunger Games",
					"genre_ids": [12, 14, 878],
					"title": "The Hunger Games",
					"vote_average": 7.1,
					"overview": "Every year in the ruins of what was once North America, the nation of Panem forces each of its twelve districts to send a teenage boy and girl to compete in the Hunger Games.  Part twisted entertainment, part government intimidation tactic, the Hunger Games are a nationally televised event in which “Tributes” must fight with one another until one survivor remains.  Pitted against highly-trained Tributes who have prepared for these Games their entire lives, Katniss is forced to rely upon her sharp instincts as well as the mentorship of drunken former victor Haymitch Abernathy.  If she’s ever to return home to District 12, Katniss must make impossible choices in the arena that weigh survival against humanity and life against love. The world will be watching.",
					"release_date": "2012-03-12"
				},
				{
					"poster_path": "/7c1JtraYsjMMnk8Md0IMoyRzqZJ.jpg",
					"vote_count": 13143,
					"video": false,
					"media_type": "movie",
					"id": 101299,
					"adult": false,
					"backdrop_path": "/aBgeZoYdrqNZ58My8oVDyQoi0Pq.jpg",
					"original_language": "en",
					"original_title": "The Hunger Games: Catching Fire",
					"genre_ids": [28, 12, 878],
					"title": "The Hunger Games: Catching Fire",
					"vote_average": 7.4,
					"overview": "Katniss Everdeen has returned home safe after winning the 74th Annual Hunger Games along with fellow tribute Peeta Mellark. Winning means that they must turn around and leave their family and close friends, embarking on a \"Victor's Tour\" of the districts. Along the way Katniss senses that a rebellion is simmering, but the Capitol is still very much in control as President Snow prepares the 75th Annual Hunger Games (The Quarter Quell) - a competition that could change Panem forever.",
					"release_date": "2013-11-15"
				},
				{
					"poster_path": "/ezHakxJHVXdPI6h3TKssEwXYtsg.jpg",
					"vote_count": 11922,
					"video": false,
					"media_type": "movie",
					"id": 131631,
					"adult": false,
					"backdrop_path": "/8PVoaWsrwbVww3AZH62dsWy877A.jpg",
					"original_language": "en",
					"original_title": "The Hunger Games: Mockingjay - Part 1",
					"genre_ids": [12, 878, 53],
					"title": "The Hunger Games: Mockingjay - Part 1",
					"vote_average": 6.8,
					"overview": "Katniss Everdeen reluctantly becomes the symbol of a mass rebellion against the autocratic Capitol.",
					"release_date": "2014-11-19"
				}
			],
			"gender": 2
		}
	]
}
